rappislack/__init__.py
rappislack/main.py
rappislack-1.5.0.dist-info/METADATA
rappislack-1.5.0.dist-info/WHEEL
rappislack-1.5.0.dist-info/top_level.txt
rappislack-1.5.0.dist-info/RECORD
