Metadata-Version: 2.1
Name: rappislack
Version: 1.5.0
Summary: Envia mensajes a un channel de slack mediante un webhook
Home-page: UNKNOWN
Author: Agustín Aguirre
Author-email: aguirreagustinariel@gmail.com
License: UNKNOWN
Platform: UNKNOWN
Classifier: Programming Language :: Python :: 3
Classifier: Operating System :: OS Independent
